{"run_number": "1682306638593996", "step_name": "hello", "task_id": "2", "attempt_id": 0, "name": "_success", "content_type": "gzip+pickle-v2", "type": "metaflow.artifact", "sha": "69e77141c3eb7a8c9ce864251d70c02723f29332", "ds_type": "local", "location": ":root:/Users/eviljimmy/Desktop/USF/2023_Spring/MLOps/Labs/mlops/notebook/.metaflow", "flow_id": "HelloWorldFlow", "user_name": "eviljimmy", "tags": [], "system_tags": ["metaflow_version:2.8.3", "user:eviljimmy", "python_version:3.9.16", "runtime:dev"], "ts_epoch": 1682306639577}